pytest_only/__init__.py
pytest_only/plugin.py
pytest_only/py.typed
dycw_pytest_only-2.1.1.dist-info/METADATA
dycw_pytest_only-2.1.1.dist-info/WHEEL
dycw_pytest_only-2.1.1.dist-info/entry_points.txt
dycw_pytest_only-2.1.1.dist-info/RECORD
