Metadata-Version: 2.4
Name: dycw-pytest-only
Version: 2.1.1
Author-email: Derek Wan <d.wan@icloud.com>
Requires-Python: >=3.9
Requires-Dist: pytest>=8.0.0
